scriptenv/__init__.py
scriptenv/builder.py
scriptenv/cli.py
scriptenv/config.py
scriptenv/pip.py
scriptenv/pipfile.py
scriptenv/scriptenv.py
scriptenv-0.3.0.dist-info/LICENSE
scriptenv-0.3.0.dist-info/METADATA
scriptenv-0.3.0.dist-info/WHEEL
scriptenv-0.3.0.dist-info/entry_points.txt
scriptenv-0.3.0.dist-info/top_level.txt
scriptenv-0.3.0.dist-info/RECORD
