Metadata-Version: 2.1
Name: scriptenv
Version: 0.3.0
Summary: define virtual environments within your code
Home-page: https://stefanhoelzl.github.io/scriptenv/
Author: Stefan Hoelzl
Author-email: stefanh+scriptenv@posteo.de
License: MIT
Keywords: virtualenv virtual environment venv scripting
Platform: UNKNOWN
Classifier: Development Status :: 4 - Beta
Classifier: Intended Audience :: Developers
Classifier: License :: OSI Approved :: MIT License
Classifier: Programming Language :: Python :: 3
Classifier: Programming Language :: Python :: 3.7
Classifier: Programming Language :: Python :: 3.8
Classifier: Programming Language :: Python :: 3.9
Classifier: Operating System :: MacOS :: MacOS X
Classifier: Operating System :: POSIX :: Linux
Classifier: Operating System :: Microsoft :: Windows
Classifier: Topic :: Software Development
Classifier: Topic :: System :: Software Distribution
License-File: LICENSE
Requires-Dist: pip (>=19.3)
Requires-Dist: appdirs
